pydantic_cli_model/__init__.py
pydantic_cli_model/climodel.py
pydantic_cli_model-0.1.5.dist-info/LICENSE
pydantic_cli_model-0.1.5.dist-info/METADATA
pydantic_cli_model-0.1.5.dist-info/WHEEL
pydantic_cli_model-0.1.5.dist-info/RECORD
