Metadata-Version: 2.1
Name: pydantic-cli-model
Version: 0.1.5
Summary: Parse cli arguments directly into Pydantic models with help from click!
Home-page: https://github.com/mgbvox/pydantic-cli-model
License: GPL-3.0-or-later
Author: Matthew Billman
Author-email: mgbvox@gmail.com
Requires-Python: >=3.12,<4.0
Classifier: License :: OSI Approved :: GNU General Public License v3 or later (GPLv3+)
Classifier: Programming Language :: Python :: 3
Classifier: Programming Language :: Python :: 3.12
Requires-Dist: pydantic (>=2.6.1,<3.0.0)
Project-URL: Repository, https://github.com/mgbvox/pydantic-cli-model
